do_update_fqdn/__init__.py
do_update_fqdn/do_update_fqdn.py
do_update_fqdn-0.2.0.dist-info/LICENSE
do_update_fqdn-0.2.0.dist-info/METADATA
do_update_fqdn-0.2.0.dist-info/WHEEL
do_update_fqdn-0.2.0.dist-info/entry_points.txt
do_update_fqdn-0.2.0.dist-info/top_level.txt
do_update_fqdn-0.2.0.dist-info/RECORD
