Metadata-Version: 2.1
Name: do-update-fqdn
Version: 0.2.0
Summary: Update or create a dns record through the DigitalOcean API.
Home-page: https://github.com/avollmerhaus/do-update-fqdn
Author: Aljoscha Vollmerhaus
Author-email: pydev@aljoscha.vollmerhaus.net
License: UNKNOWN
Platform: UNKNOWN
Classifier: Programming Language :: Python :: 3
Classifier: License :: OSI Approved :: MIT License
Classifier: Operating System :: POSIX :: Linux
Classifier: Environment :: Console
